{"version":1,"resource":"file:///home/zekvaneren/Programming/Codeforces/1719C.cpp","entries":[{"id":"ZI6G.cpp","timestamp":1661014511380},{"id":"plsR.cpp","timestamp":1661014634417},{"id":"VREJ.cpp","timestamp":1661027684997},{"id":"FRSI.cpp","timestamp":1661027885153},{"id":"j9Az.cpp","timestamp":1661028170043},{"id":"j5Zb.cpp","timestamp":1661028423483},{"id":"Nd1W.cpp","timestamp":1661028699287},{"id":"rf0u.cpp","timestamp":1661028854223},{"id":"OUE9.cpp","timestamp":1661086846643},{"id":"03nX.cpp","timestamp":1661087087947},{"id":"pzzH.cpp","timestamp":1661087472343},{"id":"eSv0.cpp","timestamp":1661087880930},{"id":"ktjO.cpp","timestamp":1661091111540},{"id":"QJDW.cpp","timestamp":1661091424537},{"id":"PpIV.cpp","timestamp":1661091452310},{"id":"1veY.cpp","timestamp":1661091661490},{"id":"QFuP.cpp","timestamp":1661091736384},{"id":"sHoF.cpp","timestamp":1661091939054},{"id":"Xy1m.cpp","timestamp":1661154644637},{"id":"Ebfs.cpp","timestamp":1661155583817}]}